tribushashm.cp37-win_amd64.pyd
tribushashm-1.0.5.dist-info/LICENSE
tribushashm-1.0.5.dist-info/METADATA
tribushashm-1.0.5.dist-info/WHEEL
tribushashm-1.0.5.dist-info/top_level.txt
tribushashm-1.0.5.dist-info/RECORD
