Metadata-Version: 2.1
Name: tribushashm
Version: 1.0.5
Summary: Bindings for tribus proof of work used by Denarius
Home-page: UNKNOWN
Author: UNKNOWN
Author-email: UNKNOWN
License: UNKNOWN
Platform: UNKNOWN
